{"sections":{"rich-text":{"type":"rich-text","blocks":{"caption":{"type":"caption","settings":{"caption":"DYNASTY HEADPHONE","text_style":"caption-with-letter-spacing","text_size":"medium"}},"block-0":{"type":"heading","settings":{"heading":"<p>Listen with new ears<\/p>","heading_size":"h1"}},"block-1":{"type":"text","settings":{"text":"<p>Custom titanium drivers – nestled under detachable magnetic earcups – are tuned to our tightest tolerance on performance. It's done under the watchful ear of our in-house Tonmeister. The result? More lush lows, punchier mids and crisper highs. Put simply, you'll hear magical details you've never heard before.<\/p>"}},"block-2":{"type":"button","settings":{"button_label":"Explore product landing","button_link":"","button_style_secondary":false,"button_label_2":"","button_link_2":"","button_style_secondary_2":false}}},"block_order":["caption","block-0","block-1","block-2"],"disabled":true,"settings":{"desktop_content_position":"center","content_alignment":"center","color_scheme":"background-1","full_width":true,"padding_top":52,"padding_bottom":52}},"main":{"type":"main-list-collections","custom_css":[".list-collections__item-info {height: 100%; background: rgba(0, 0, 0, 0.1); display: flex; justify-content: center; align-items: center;}",".list-collections__item-info p {font-size: 20px;}"],"settings":{"display_default_collection":true,"title":"Select The Marketing You Want To Create...","sort":"alphabetical","image_ratio":"square","columns_desktop":3,"columns_mobile":"2"}},"rich_text_mE4tmj":{"type":"rich-text","blocks":{"heading_RnU4Ea":{"type":"heading","settings":{"heading":"<p>More Designs & Categories Coming Soon...<\/p>","heading_size":"h1"}},"text_yfNdfw":{"type":"text","settings":{"text":"<p>Click the button below to get a sneak peek at what your future designs will look like.<\/p>"}},"button_Ppgt9f":{"type":"button","settings":{"button_label":"See Upcoming Collections","button_link":"https:\/\/info.myprintsource.com\/#soon","button_style_secondary":false,"button_label_2":"","button_link_2":"","button_style_secondary_2":false}}},"block_order":["heading_RnU4Ea","text_yfNdfw","button_Ppgt9f"],"settings":{"desktop_content_position":"center","content_alignment":"center","color_scheme":"background-1","full_width":true,"padding_top":40,"padding_bottom":52}},"collection-list-grid":{"type":"collection-list-grid","blocks":{"block-0":{"type":"featured_collection","settings":{"collection":"business-cards","highlight":false,"heading_color":"#ffffff","heading":"","heading_size_range":4,"heading_2":"","heading_2_size":"heading--xsmall","text_color":"#282828","overlay":"#000000","overlay_opacity":1,"link":""}},"block-1":{"type":"featured_collection","settings":{"collection":"clothing-bags","highlight":false,"heading_color":"#ffffff","heading":"","heading_size_range":4,"heading_2":"","heading_2_size":"heading--xsmall","text_color":"#282828","overlay":"#000000","overlay_opacity":1,"link":""}},"featured_collection_YtbtdM":{"type":"featured_collection","settings":{"collection":"design-services","highlight":false,"heading_color":"#282828","heading":"","heading_size_range":4,"heading_2":"","heading_2_size":"heading--xsmall","text_color":"#282828","overlay":"#000000","overlay_opacity":1,"link":""}},"featured_collection":{"type":"featured_collection","settings":{"collection":"invitations-stationery","highlight":false,"heading_color":"#ffffff","heading":"","heading_size_range":4,"heading_2":"","heading_2_size":"heading--xsmall","text_color":"#282828","overlay":"#000000","overlay_opacity":1,"link":""}}},"block_order":["block-0","block-1","featured_collection_YtbtdM","featured_collection"],"disabled":true,"settings":{"section_background":"#f5f5f5","heading_color":"#282828","text_color":"#282828","color_card":"#ffffff","number_column":4,"collection_layout":"none","collection-item_layout":"none","heading":"","heading_size_range":1,"layout":"after","text_position":"left","description":"","description_size":"heading--xsmall","box_style":"none-border","padding_top":36,"padding_bottom":36,"margin_desktop":"","margin_tablet":"","margin_mobile":""}}},"order":["rich-text","main","rich_text_mE4tmj","collection-list-grid"]}